<xml xmlns="https://developers.google.com/blockly/xml"><variables><variable id="vEi8~};bTOUCo4pTq%$3">curr</variable><variable id="#8*K1p~Cx{k#[zGm$]U^">currency</variable><variable id="n+*OvT.EqQPaXAf:Wxj)">df</variable><variable id=".UJ^m9s+zAS/C=j.!$Z(">exch</variable><variable id="Sni[E/o|gC#S!8OeDtHy">rate_usd</variable><variable id=",h1~,1SKQ}?Dl9fmsOTe">rate</variable></variables><block type="import_as" id="lKqI[3zoMi=vWJ~[Kbgi" x="34" y="31"><field name="MODULE">rpa</field><field name="NAME">r</field><next><block type="import_as" id=";MP87@~0!;W{aO`n|J:4"><field name="MODULE">pandas</field><field name="NAME">pd</field></block></next></block><block type="variables_set" id=",)jZb.lx]tb:xmS{lv,}" x="29" y="130"><field name="VAR" id="vEi8~};bTOUCo4pTq%$3">curr</field><value name="VALUE"><block type="lists_create_with" id="#COA-rXza1^bR`C,X=l%"><mutation items="5"></mutation><value name="ADD0"><block type="text" id="M;vxNFz%bDt.F!07*j0#"><field name="TEXT">Australian</field></block></value><value name="ADD1"><block type="text" id="_T=P(?kkRDGhCDeHS^cm"><field name="TEXT">Malaysian</field></block></value><value name="ADD2"><block type="text" id="sH6s;ZZ2-+`HEAPh=.,5"><field name="TEXT">Singapore</field></block></value><value name="ADD3"><block type="text" id="X)[UUYT`+=+;v3+TqM/Y"><field name="TEXT">Hong Kong</field></block></value><value name="ADD4"><block type="text" id="bBq#Em?}kr~Q[y8c).Yi"><field name="TEXT">Chinese Yuan</field></block></value></block></value></block><block type="initialize" id="L2UZ|zAR}%)s9oGi9@@t" x="31" y="304"><field name="NAME">r</field><field name="ACTION">visual_automation</field><value name="BOOLEAN"><shadow type="logic_boolean" id="YGeRh-oY5v6(jcq*l$^l"><field name="BOOL">TRUE</field></shadow></value></block><block type="connect_block" id="7;y]qnHp[4JXqLFG3d#:" x="42" y="427"><value name="CONNECTOR"><block type="url" id="q}sJqlG~:]0eh,@mr$Cd"><field name="NAME">r</field><value name="URL"><block type="text" id="OL;ifxRP![))q$cCNz9B"><field name="TEXT">https://www.google.com.my/</field></block></value></block></value><next><block type="wait" id="Qc%mz--O.Sj@:%o?fE0%"><field name="NAME">r</field><field name="TIME">5</field><next><block type="type1" id=":uyIRQTk^w%]@DJBy@?A"><field name="NAME">r</field><value name="ELEMENT_IDENTIFIER"><shadow type="text" id="_wN{w#IZ|d0P`tkBDk!N"><field name="TEXT">gLFyf gsfi</field></shadow></value><value name="TEXT_TO_TYPE"><shadow type="text" id="ttk#[uiH``eUh[9ML=NH"><field name="TEXT">currency converter[enter]</field></shadow></value><next><block type="wait" id=":Y/VxF_{rZ.lQj90`.d~"><field name="NAME">r</field><field name="TIME">5</field><next><block type="variables_set" id="5:l7(Pc^=vYk}x^SNGCR"><field name="VAR" id="Sni[E/o|gC#S!8OeDtHy">rate_usd</field><value name="VALUE"><block type="lists_create_with" id="`(?PBYP:SYHrcaP_fd3!"><mutation items="0"></mutation></block></value></block></next></block></next></block></next></block></next></block><block type="controls_forEach" id="_|ilUP~{KFMGPe2hFJ-8" x="38" y="658"><field name="VAR" id="#8*K1p~Cx{k#[zGm$]U^">currency</field><value name="LIST"><block type="variables_get" id="M$ce91zj+,UFLT~gRZ]K"><field name="VAR" id="vEi8~};bTOUCo4pTq%$3">curr</field></block></value><statement name="DO"><block type="variables_set" id="S!R,49kU+19iM6]Gg1q9"><field name="VAR" id=".UJ^m9s+zAS/C=j.!$Z(">exch</field><value name="VALUE"><block type="create_dict" id="e1~})gF]O91gp@JCCDD1"></block></value><next><block type="click" id="J==YJ2*Kkk$mJG0MBY4M"><field name="NAME">r</field><field name="INPUT">click</field><value name="ELEMENT_IDENTIFIER"><shadow type="text" id="C,33%mq][a*3scwDIGdP"><field name="TEXT">J8cLR</field></shadow></value><next><block type="type1" id="-nQvLv%,AN~.:woQBc9s"><field name="NAME">r</field><value name="ELEMENT_IDENTIFIER"><shadow type="text" id="O!sw(xe@#;I.T@exSj9B"><field name="TEXT">J8cLR</field></shadow></value><value name="TEXT_TO_TYPE"><shadow type="text" id=";WZMhq1]|},^X6dV.n30"><field name="TEXT">currency</field></shadow><block type="variables_get" id="7uYm%[_mvahZ5lx;YduG"><field name="VAR" id="#8*K1p~Cx{k#[zGm$]U^">currency</field></block></value><next><block type="click" id="?eihz:OlL(V*^7sH]9fm"><field name="NAME">r</field><field name="INPUT">click</field><value name="ELEMENT_IDENTIFIER"><shadow type="text" id="2,m_#dGKactYFHL6qxxu"><field name="TEXT">J8cLR</field></shadow></value><next><block type="variables_set" id="G1^R+[r/*vK4RH^XtsPI"><field name="VAR" id=",h1~,1SKQ}?Dl9fmsOTe">rate</field><value name="VALUE"><block type="read1" id="HC8;i[(1tX}_B_hypdO:"><field name="NAME">r</field><value name="ELEMENT_IDENTIFIER"><shadow type="text" id="Ha$?58Sd@=@vK5,v)r44"><field name="TEXT">a61j6 vk_gy vk_sh Hg3mWc</field></shadow></value></block></value><next><block type="update_dic" id="~ZSBm_;?V_w#nxA[jP[g"><value name="DICTIONARY"><block type="variables_get" id="2w.;ib#(;HM%%oDq5o_="><field name="VAR" id=".UJ^m9s+zAS/C=j.!$Z(">exch</field></block></value><value name="KEY"><block type="text" id="xP$E9LLv;4ym7t9Ye)Ia"><field name="TEXT">currency</field></block></value><value name="VALUE"><block type="variables_get" id=")$%@3N+k}otzI6x*|B6+"><field name="VAR" id="#8*K1p~Cx{k#[zGm$]U^">currency</field></block></value><next><block type="update_dic" id="G6Z(W[BO5YG36a=:Gf1Q"><value name="DICTIONARY"><block type="variables_get" id="nb%06Rn$eyPDnAjFxtjG"><field name="VAR" id=".UJ^m9s+zAS/C=j.!$Z(">exch</field></block></value><value name="KEY"><block type="text" id="5$bKc8]oqO0JrT}R26f0"><field name="TEXT">rate</field></block></value><value name="VALUE"><block type="variables_get" id=")G3+@Q(?^fzvz[}42x[5"><field name="VAR" id=",h1~,1SKQ}?Dl9fmsOTe">rate</field></block></value><next><block type="lists_setIndex" id="F^7f=Rk9F1n^%C-WQf5i"><mutation at="false"></mutation><field name="MODE">INSERT</field><field name="WHERE">LAST</field><value name="LIST"><block type="variables_get" id="]xX2X`nXrcv-@wBF%e|r"><field name="VAR" id="Sni[E/o|gC#S!8OeDtHy">rate_usd</field></block></value><value name="TO"><block type="variables_get" id="DI@|KL43c%:rhZ%ct6p4"><field name="VAR" id=".UJ^m9s+zAS/C=j.!$Z(">exch</field></block></value></block></next></block></next></block></next></block></next></block></next></block></next></block></next></block></statement></block><block type="init_close_pack_update" id="MLvo(yX;xK,xo(9M}ghz" x="52" y="1085"><field name="NAME">r</field><field name="FUNCTION">close()</field><next><block type="variables_set" id="X0u:`g-xm3Z9r)G=L|+}"><field name="VAR" id="n+*OvT.EqQPaXAf:Wxj)">df</field><value name="VALUE"><block type="dataframe_pandas" id="cZIDG0kE*d{4RQmEz|RW"><field name="NAME">pd</field><value name="INPUT"><block type="variables_get" id="145q:nyF8!JT}Nobe$6G"><field name="VAR" id="Sni[E/o|gC#S!8OeDtHy">rate_usd</field></block></value></block></value><next><block type="text_print" id="Q-@T:[}{ACAy(mviuuHN"><value name="TEXT"><shadow type="text" id="?/~yMn[A#Ik#sT?#ENuQ"><field name="TEXT">abc</field></shadow><block type="variables_get" id="D=F=|3bv^kA?Hb1SCjVb"><field name="VAR" id="n+*OvT.EqQPaXAf:Wxj)">df</field></block></value></block></next></block></next></block></xml>